{
    "Analysis": {
        "AeroMechanical": "",
        "CFD": "",
        "CoupledAeroMechanical": "",
        "Structural": {
            "Mechanical": {
                "2Dmodel_sim2_CQUAD8_ElSize_1mm": {
                    "SolidMaterial": [
                        "AISI_Steel_4340"
                    ],
                    "is2D": true,
                    "isTransient": false,
                    "LocalStorage": [
                        "LocalStorage_id_num_1--2Dmodel_sim2_CQUAD8_ElSize_1mm"
                    ],
                    "isHarmonic": false,
                    "is3D": false,
                    "Geometry": [
                        "2DMODEL"
                    ],
                    "Boundary": [
                        "Fixed(1)--2Dmodel_sim2_CQUAD8_ElSize_1mm"
                    ],
                    "Mesh": [
                        "2Dmodel_fem2_CQUAD8_ElSize_1mm"
                    ],
                    "ToolVersion": "v12.0.2.9",
                    "Result": [
                        "2dmodel_sim2-structural--2Dmodel_sim2_CQUAD8_ElSize_1mm"
                    ],
                    "LastModificationDate": 1631016648.0,
                    "FileSize": 3459786,
                    "isSteadyState": true,
                    "People": [
                        "Shyam"
                    ],
                    "FileNameOriginal": "2Dmodel_sim2",
                    "FileNameAlias": "2Dmodel_sim2_CQUAD8_ElSize_1mm",
                    "PointLoad": [
                        "FrontLoad--2Dmodel_sim2_CQUAD8_ElSize_1mm",
                        "TopLoad--2Dmodel_sim2_CQUAD8_ElSize_1mm"
                    ]
                }
            },
            "Thermomechanical": ""
        }
    },
    "Material": {
        "FluidMaterial": "",
        "SolidMaterial": {
            "AISI_Steel_4340": {
                "R0": "2.5",
                "R45": "3",
                "R90": "2.7",
                "MaterialCategory": "METAL",
                "MaterialSubCategory": "Carbon Steel",
                "Density": [
                    "Density_7.85e-06_AISI_Steel_4340"
                ],
                "ModulusOfElasticity": [
                    "ModulusOfElasticity_193000000_AISI_Steel_4340"
                ],
                "PoissonRatio": "0.284",
                "TypeOfNonlinearity": "1",
                "YieldFunctionCriterion": "1",
                "HardeningRule": "1",
                "YieldStrength": [
                    "YieldStrength_1178000_AISI_Steel_4340"
                ],
                "UltimateTensileStrength": [
                    "UltimateTensileStrength_1240000_AISI_Steel_4340"
                ],
                "FatigueStrengthCoefficient": [
                    "FatigueStrengthCoefficient_1917000_AISI_Steel_4340"
                ],
                "FatigueStrengthExponent": "-0.099",
                "FatigueDuctilityCoefficient": "1.122",
                "FatigueDuctilityExponent": "-0.72",
                "CyclicStrengthCoefficient": [
                    "CyclicStrengthCoefficient_1887000_AISI_Steel_4340"
                ],
                "CyclicStrainHardeningExponent": "0.137",
                "InitialStrain": [
                    "InitialStrain_0.02_AISI_Steel_4340"
                ],
                "HardeningExponent": "0.22",
                "StrengthCoefficient": [
                    "StrengthCoefficient_2182.004_AISI_Steel_4340"
                ],
                "ThermalExpansionCoefficient": [
                    "ThermalExpansionCoefficient_1.23e-051_AISI_Steel_4340"
                ],
                "ThermalConductivity": [
                    "ThermalConductivity_44500_AISI_Steel_4340"
                ],
                "SpecificHeat": [
                    "SpecificHeat_475000000_AISI_Steel_4340"
                ],
                "CrosshatchPattern": "Steel"
            }
        }
    },
    "Boundary": {
        "Fixed(1)--2Dmodel_sim2_CQUAD8_ElSize_1mm": {
            "FixedConstraint": [
                "FixedConstraint_id_num_1--2Dmodel_sim2_CQUAD8_ElSize_1mm"
            ]
        }
    },
    "People": {
        "Shyam": {
            "Name": "Shyam"
        },
        "Chethan": {
            "Name": "Chethan"
        }
    },
    "Geometry": {
        "2DMODEL": {
            "SolidMaterial": [
                "AISI_Steel_4340"
            ],
            "is2D": true,
            "is3D": false,
            "LastModificationDate": 1613118225.0,
            "FileSize": 37850,
            "FileNameOriginal": "2DMODEL",
            "FileNameAlias": "2DMODEL",
            "Line": [
                "Line4--2DMODEL"
            ],
            "Component": [
                "2DMODEL--2DMODEL"
            ],
            "Edge": [
                "LOADINGEDGE--2DMODEL",
                "TOPEDGE--2DMODEL"
            ]
        }
    },
    "Loads": {
        "CyclicLoads": "",
        "HeatFlux": "",
        "MomentLoad": "",
        "PointLoad": {
            "FrontLoad--2Dmodel_sim2_CQUAD8_ElSize_1mm": {
                "Name": "FrontLoad",
                "types": [
                    "FORCE"
                ],
                "CSYSOption": 5,
                "observeNode1": "Observe Node 1",
                "observeNode2": "Observe Node 2",
                "observeNode3": "Observe Node 3",
                "observeNode4": "Observe Node 4",
                "distributionType": 1,
                "DistributionField": "NA",
                "Edge": [
                    "LOADINGEDGE--2DMODEL"
                ],
                "Force": [
                    "Force_1000000.0_FrontLoad--2Dmodel_sim2_CQUAD8_ElSize_1mm"
                ]
            },
            "TopLoad--2Dmodel_sim2_CQUAD8_ElSize_1mm": {
                "Name": "TopLoad",
                "types": [
                    "FORCE",
                    "LOAD"
                ],
                "CSYSOption": 5,
                "observeNode1": "Observe Node 1",
                "observeNode2": "Observe Node 2",
                "observeNode3": "Observe Node 3",
                "observeNode4": "Observe Node 4",
                "distributionType": 1,
                "DistributionField": "NA",
                "Edge": [
                    "TOPEDGE--2DMODEL"
                ],
                "Force": [
                    "Force_2500000.0_TopLoad--2Dmodel_sim2_CQUAD8_ElSize_1mm"
                ]
            }
        },
        "PressureLoad": "",
        "UDL": ""
    },
    "Mesh": {
        "2Dmodel_fem2_CQUAD8_ElSize_1mm": {
            "MeshVolume": [
                "2d_mesh(1)--2Dmodel_fem2_CQUAD8_ElSize_1mm"
            ],
            "LastModificationDate": 1631016648.0,
            "FileSize": 5585387,
            "is2D": true,
            "is3D": false,
            "FileNameOriginal": "2Dmodel_fem2",
            "FileNameAlias": "2Dmodel_fem2_CQUAD8_ElSize_1mm"
        }
    },
    "Preprocessing": "",
    "Result": {
        "2dmodel_sim2-structural--2Dmodel_sim2_CQUAD8_ElSize_1mm": {
            "LastModificationDate": 1631016591.0,
            "FileSize": 66588640,
            "DisplacementNodal": [
                "DisplacementNodal_LOADINGEDGE_id_num_3--2Dmodel_sim2_CQUAD8_ElSize_1mm",
                "DisplacementNodal_Model_id_num_4--2Dmodel_sim2_CQUAD8_ElSize_1mm",
                "DisplacementNodal_TOPEDGE_id_num_5--2Dmodel_sim2_CQUAD8_ElSize_1mm"
            ],
            "ReactionForceNodal": [
                "ReactionForceNodal_LOADINGEDGE_id_num_3--2Dmodel_sim2_CQUAD8_ElSize_1mm",
                "ReactionForceNodal_Model_id_num_4--2Dmodel_sim2_CQUAD8_ElSize_1mm",
                "ReactionForceNodal_TOPEDGE_id_num_5--2Dmodel_sim2_CQUAD8_ElSize_1mm"
            ],
            "ReactionMomentNodal": [
                "ReactionMomentNodal_LOADINGEDGE_id_num_3--2Dmodel_sim2_CQUAD8_ElSize_1mm",
                "ReactionMomentNodal_Model_id_num_4--2Dmodel_sim2_CQUAD8_ElSize_1mm",
                "ReactionMomentNodal_TOPEDGE_id_num_5--2Dmodel_sim2_CQUAD8_ElSize_1mm"
            ],
            "RotationNodal": [
                "RotationNodal_LOADINGEDGE_id_num_3--2Dmodel_sim2_CQUAD8_ElSize_1mm",
                "RotationNodal_Model_id_num_4--2Dmodel_sim2_CQUAD8_ElSize_1mm",
                "RotationNodal_TOPEDGE_id_num_5--2Dmodel_sim2_CQUAD8_ElSize_1mm"
            ],
            "StressElementNodal": [
                "StressElementNodal_LOADINGEDGE_id_num_3--2Dmodel_sim2_CQUAD8_ElSize_1mm",
                "StressElementNodal_Model_id_num_4--2Dmodel_sim2_CQUAD8_ElSize_1mm",
                "StressElementNodal_TOPEDGE_id_num_5--2Dmodel_sim2_CQUAD8_ElSize_1mm"
            ],
            "StressElemental": [
                "StressElemental_Model_id_num_4--2Dmodel_sim2_CQUAD8_ElSize_1mm"
            ],
            "ConfluencePage": [
                "ConfluencePage_id_num_5--2Dmodel_sim2_CQUAD8_ElSize_1mm"
            ],
            "PPT": [
                "PPT_id_num_5--2Dmodel_sim2_CQUAD8_ElSize_1mm"
            ]
        }
    },
    "StorageLocation": {
        "CloudStorage": "",
        "LocalStorage": {
            "LocalStorage_id_num_1--2Dmodel_sim2_CQUAD8_ElSize_1mm": {
                "GID": "z003hz2y",
                "MachineName": "demlhw7sw110x"
            },
            "LocalStorage_id_num_6--2Dmodel_sim2_CQUAD8_ElSize_1mm": {
                "GID": "",
                "MachineName": ""
            }
        },
        "ServerStorage": "",
        "TeamcenterStorage": ""
    },
    "Supplier": "",
    "QuantitativeMetric": {
        "Angle": "",
        "CyclicStrengthCoefficient": {
            "CyclicStrengthCoefficient_1887000_AISI_Steel_4340": {
                "hasMagnitude": "1887000",
                "hasUnit": "mN/mm^2(kPa)"
            }
        },
        "Density": {
            "Density_7.85e-06_AISI_Steel_4340": {
                "hasMagnitude": "7.85e-06",
                "hasUnit": "kg/mm^3"
            }
        },
        "ElasticStrength": "",
        "FatigueStrengthCoefficient": {
            "FatigueStrengthCoefficient_1917000_AISI_Steel_4340": {
                "hasMagnitude": "1917000",
                "hasUnit": "mN/mm^2(kPa)"
            }
        },
        "Force": {
            "Force_1000000.0_FrontLoad--2Dmodel_sim2_CQUAD8_ElSize_1mm": {
                "hasMagnitude": 1000000.0,
                "hasUnit": "N"
            },
            "Force_2500000.0_TopLoad--2Dmodel_sim2_CQUAD8_ElSize_1mm": {
                "hasMagnitude": 2500000.0,
                "hasUnit": "N"
            }
        },
        "Height": "",
        "Independent": "",
        "InitialStrain": {
            "InitialStrain_0.02_AISI_Steel_4340": {
                "hasMagnitude": "0.02",
                "hasUnit": "mm/mm"
            }
        },
        "Length": {
            "ElementSize_1mm--2Dmodel_fem2_CQUAD8_ElSize_1mm": {
                "hasMagnitude": 1.0,
                "hasUnit": "mm"
            }
        },
        "Mass_Flow": "",
        "ModulusOfElasticity": {
            "ModulusOfElasticity_193000000_AISI_Steel_4340": {
                "hasMagnitude": "193000000",
                "hasUnit": "mN/mm^2(kPa)"
            }
        },
        "Moment": "",
        "PoissonRatioArray": "",
        "Pressure": "",
        "ShearModulus": "",
        "SpecificHeat": {
            "SpecificHeat_475000000_AISI_Steel_4340": {
                "hasMagnitude": "475000000",
                "hasUnit": "microJ/kg-dK"
            }
        },
        "StrengthCoefficient": {
            "StrengthCoefficient_2182.004_AISI_Steel_4340": {
                "hasMagnitude": "2182.004",
                "hasUnit": "N/mm^2(MPa)"
            }
        },
        "Stress": "",
        "Temperature": "",
        "ThermalConductivity": {
            "ThermalConductivity_44500_AISI_Steel_4340": {
                "hasMagnitude": "44500",
                "hasUnit": "microW/mm-dC"
            }
        },
        "ThermalExpansionCoefficient": {
            "ThermalExpansionCoefficient_1.23e-051_AISI_Steel_4340": {
                "hasMagnitude": "1.23e-051",
                "hasUnit": "/dC"
            }
        },
        "Thickness": "",
        "TurbulenceIntensity": "",
        "UltimateTensileStrength": {
            "UltimateTensileStrength_1240000_AISI_Steel_4340": {
                "hasMagnitude": "1240000",
                "hasUnit": "mN/mm^2(kPa)"
            }
        },
        "Velocity": "",
        "Viscosity": "",
        "Width": "",
        "XDirection": "",
        "YDirection": "",
        "YieldStrength": {
            "YieldStrength_1178000_AISI_Steel_4340": {
                "hasMagnitude": "1178000",
                "hasUnit": "mN/mm^2(kPa)"
            }
        },
        "ZDirection": ""
    },
    "BoundaryCondition": {
        "FEABoundaryCondition": {
            "FEAConstraintBC": {
                "AntiSymmetricConstraint": "",
                "AutomaticCoupling": "",
                "CylindricalConstraint": "",
                "EnforcedDisplacementConstraint": "",
                "FixedConstraint": {
                    "FixedConstraint_id_num_1--2Dmodel_sim2_CQUAD8_ElSize_1mm": {
                        "Name": "Fixed(1)",
                        "CSYSOption": 0,
                        "DOF1": 0.0,
                        "DOF2": 0.0,
                        "DOF3": 0.0,
                        "DOF4": 0.0,
                        "DOF5": 0.0,
                        "DOF6": 0.0,
                        "DescriptorName": "fixedConstraint",
                        "DistributionType": 5,
                        "ConstraintType": "SPC"
                    }
                },
                "FixedRotationConstraint": "",
                "FixedTranslationConstraint": "",
                "ManualCoupling": "",
                "PinnedConstraint": "",
                "RollerConstraint": "",
                "SimplySupportedConstraint": "",
                "SliderConstraint": "",
                "SymmetricConstraint": "",
                "UserDefinedConstraint": ""
            },
            "FEAInteractionBC": {
                "MechanicalContact": "",
                "ThermalContact": ""
            }
        },
        "CFDBoundaryCondition": {
            "CFDConstraintBC": {
                "FrictionWallBC": "",
                "TotalPressureBC": "",
                "VelocityBC": "",
                "MassFlowBC": "",
                "MovingWallBC": "",
                "SmoothWallBC": "",
                "StationaryWallBC": ""
            },
            "CFDInteractionBC": ""
        },
        "GenericBoundaryCondition": {
            "PressureBC": ""
        }
    },
    "PostProcessing": {
        "Parameters": {
            "CFDParameters": {
                "AreaAveragedDynamicPressure": "",
                "AreaAveragedPressure": "",
                "AreaAveragedTotalPressure": "",
                "MassAveragedDynamicPressure": "",
                "MassAveragedPressure": "",
                "MassAveragedTotalPressure": "",
                "MassFlowRate": ""
            },
            "FEAParameters": {
                "DisplacementNodal": {
                    "DisplacementNodal_LOADINGEDGE_id_num_3--2Dmodel_sim2_CQUAD8_ElSize_1mm": {
                        "hasUnit": "mm",
                        "Magnitude-Maximum": "0.12007906287908554",
                        "Magnitude-Minimum": "0.11705991625785828",
                        "X-Maximum": "0.026382528245449066",
                        "X-Minimum": "-0.020889997482299805",
                        "Y-Maximum": "0.0",
                        "Y-Minimum": "0.0",
                        "Z-Maximum": "0.1172824427485466",
                        "Z-Minimum": "0.11619240045547485"
                    },
                    "DisplacementNodal_Model_id_num_4--2Dmodel_sim2_CQUAD8_ElSize_1mm": {
                        "hasUnit": "mm",
                        "Magnitude-Maximum": "0.12007906287908554",
                        "Magnitude-Minimum": "0.0",
                        "X-Maximum": "0.026382528245449066",
                        "X-Minimum": "-0.021248940378427505",
                        "Y-Maximum": "0.0",
                        "Y-Minimum": "0.0",
                        "Z-Maximum": "0.1172824427485466",
                        "Z-Minimum": "0.0"
                    },
                    "DisplacementNodal_TOPEDGE_id_num_5--2Dmodel_sim2_CQUAD8_ElSize_1mm": {
                        "hasUnit": "mm",
                        "Magnitude-Maximum": "0.11912834644317627",
                        "Magnitude-Minimum": "0.0",
                        "X-Maximum": "0.025876648724079132",
                        "X-Minimum": "-0.021248940378427505",
                        "Y-Maximum": "0.0",
                        "Y-Minimum": "0.0",
                        "Z-Maximum": "0.1172824427485466",
                        "Z-Minimum": "0.0"
                    }
                },
                "ReactionForceNodal": {
                    "ReactionForceNodal_LOADINGEDGE_id_num_3--2Dmodel_sim2_CQUAD8_ElSize_1mm": {
                        "hasUnit": "milli-newton",
                        "Magnitude-Maximum": "0.0",
                        "Magnitude-Minimum": "0.0",
                        "X-Maximum": "0.0",
                        "X-Minimum": "0.0",
                        "Y-Maximum": "0.0",
                        "Y-Minimum": "0.0",
                        "Z-Maximum": "0.0",
                        "Z-Minimum": "0.0"
                    },
                    "ReactionForceNodal_Model_id_num_4--2Dmodel_sim2_CQUAD8_ElSize_1mm": {
                        "hasUnit": "milli-newton",
                        "Magnitude-Maximum": "242570.8125",
                        "Magnitude-Minimum": "0.0",
                        "X-Maximum": "231744.546875",
                        "X-Minimum": "-240613.25",
                        "Y-Maximum": "0.0",
                        "Y-Minimum": "0.0",
                        "Z-Maximum": "0.0",
                        "Z-Minimum": "-47227.640625"
                    },
                    "ReactionForceNodal_TOPEDGE_id_num_5--2Dmodel_sim2_CQUAD8_ElSize_1mm": {
                        "hasUnit": "milli-newton",
                        "Magnitude-Maximum": "120497.625",
                        "Magnitude-Minimum": "0.0",
                        "X-Maximum": "110856.7890625",
                        "X-Minimum": "0.0",
                        "Y-Maximum": "0.0",
                        "Y-Minimum": "0.0",
                        "Z-Maximum": "0.0",
                        "Z-Minimum": "-47227.640625"
                    }
                },
                "ReactionMomentNodal": {
                    "ReactionMomentNodal_LOADINGEDGE_id_num_3--2Dmodel_sim2_CQUAD8_ElSize_1mm": {
                        "hasUnit": "milli-newton-mm",
                        "Magnitude-Maximum": "0.0",
                        "Magnitude-Minimum": "0.0",
                        "X-Maximum": "0.0",
                        "X-Minimum": "0.0",
                        "Y-Maximum": "0.0",
                        "Y-Minimum": "0.0",
                        "Z-Maximum": "0.0",
                        "Z-Minimum": "0.0"
                    },
                    "ReactionMomentNodal_Model_id_num_4--2Dmodel_sim2_CQUAD8_ElSize_1mm": {
                        "hasUnit": "milli-newton-mm",
                        "Magnitude-Maximum": "0.0",
                        "Magnitude-Minimum": "0.0",
                        "X-Maximum": "0.0",
                        "X-Minimum": "0.0",
                        "Y-Maximum": "0.0",
                        "Y-Minimum": "0.0",
                        "Z-Maximum": "0.0",
                        "Z-Minimum": "0.0"
                    },
                    "ReactionMomentNodal_TOPEDGE_id_num_5--2Dmodel_sim2_CQUAD8_ElSize_1mm": {
                        "hasUnit": "milli-newton-mm",
                        "Magnitude-Maximum": "0.0",
                        "Magnitude-Minimum": "0.0",
                        "X-Maximum": "0.0",
                        "X-Minimum": "0.0",
                        "Y-Maximum": "0.0",
                        "Y-Minimum": "0.0",
                        "Z-Maximum": "0.0",
                        "Z-Minimum": "0.0"
                    }
                },
                "RotationNodal": {
                    "RotationNodal_LOADINGEDGE_id_num_3--2Dmodel_sim2_CQUAD8_ElSize_1mm": {
                        "hasUnit": "deg",
                        "Magnitude-Maximum": "0.0",
                        "Magnitude-Minimum": "0.0",
                        "X-Maximum": "0.0",
                        "X-Minimum": "0.0",
                        "Y-Maximum": "0.0",
                        "Y-Minimum": "0.0",
                        "Z-Maximum": "0.0",
                        "Z-Minimum": "0.0"
                    },
                    "RotationNodal_Model_id_num_4--2Dmodel_sim2_CQUAD8_ElSize_1mm": {
                        "hasUnit": "deg",
                        "Magnitude-Maximum": "0.0",
                        "Magnitude-Minimum": "0.0",
                        "X-Maximum": "0.0",
                        "X-Minimum": "0.0",
                        "Y-Maximum": "0.0",
                        "Y-Minimum": "0.0",
                        "Z-Maximum": "0.0",
                        "Z-Minimum": "0.0"
                    },
                    "RotationNodal_TOPEDGE_id_num_5--2Dmodel_sim2_CQUAD8_ElSize_1mm": {
                        "hasUnit": "deg",
                        "Magnitude-Maximum": "0.0",
                        "Magnitude-Minimum": "0.0",
                        "X-Maximum": "0.0",
                        "X-Minimum": "0.0",
                        "Y-Maximum": "0.0",
                        "Y-Minimum": "0.0",
                        "Z-Maximum": "0.0",
                        "Z-Minimum": "0.0"
                    }
                },
                "StressElementNodal": {
                    "StressElementNodal_LOADINGEDGE_id_num_3--2Dmodel_sim2_CQUAD8_ElSize_1mm": {
                        "hasUnit": "milli-newton/mm^2",
                        "Determinant-Maximum": "0.0",
                        "Determinant-Minimum": "0.0",
                        "MaximumPrincipal-Maximum": "2000.17578125",
                        "MaximumPrincipal-Minimum": "1996.697021484375",
                        "MaximumShear-Maximum": "1023.908447265625",
                        "MaximumShear-Minimum": "998.7938232421875",
                        "Mean-Maximum": "1238.240966796875",
                        "Mean-Minimum": "650.6502685546875",
                        "MiddlePrincipal-Maximum": "1714.6065673828125",
                        "MiddlePrincipal-Minimum": "-7.44648787076585e-11",
                        "MinimumPrincipal-Maximum": "9.142695489572361e-10",
                        "MinimumPrincipal-Minimum": "-47.933021545410156",
                        "Octahedral-Maximum": "954.2529296875",
                        "Octahedral-Minimum": "816.5093383789062",
                        "VonMises-Maximum": "2024.276123046875",
                        "VonMises-Minimum": "1732.077880859375",
                        "WorstPrincipal-Maximum": "2000.17578125",
                        "WorstPrincipal-Minimum": "1996.697021484375",
                        "XX-Maximum": "2000.17578125",
                        "XX-Minimum": "1996.69189453125",
                        "XY-Maximum": "0.0",
                        "XY-Minimum": "0.0",
                        "YY-Maximum": "0.0",
                        "YY-Minimum": "0.0",
                        "YZ-Maximum": "0.0",
                        "YZ-Minimum": "0.0",
                        "ZX-Maximum": "0.16660860180854797",
                        "ZX-Minimum": "-3.1844024658203125",
                        "ZZ-Maximum": "1714.6065673828125",
                        "ZZ-Minimum": "-47.933013916015625"
                    },
                    "StressElementNodal_Model_id_num_4--2Dmodel_sim2_CQUAD8_ElSize_1mm": {
                        "hasUnit": "milli-newton/mm^2",
                        "Determinant-Maximum": "0.0",
                        "Determinant-Minimum": "0.0",
                        "MaximumPrincipal-Maximum": "115425.6796875",
                        "MaximumPrincipal-Minimum": "-1.4347278920467943e-09",
                        "MaximumShear-Maximum": "57712.83984375",
                        "MaximumShear-Minimum": "833.3782348632812",
                        "Mean-Maximum": "45012.91796875",
                        "Mean-Minimum": "-44518.328125",
                        "MiddlePrincipal-Maximum": "19613.07421875",
                        "MiddlePrincipal-Minimum": "-18480.125",
                        "MinimumPrincipal-Maximum": "4.842386260861531e-07",
                        "MinimumPrincipal-Minimum": "-115074.859375",
                        "Octahedral-Maximum": "50458.21484375",
                        "Octahedral-Minimum": "680.4607543945312",
                        "VonMises-Maximum": "107038.0390625",
                        "VonMises-Minimum": "1443.4752197265625",
                        "WorstPrincipal-Maximum": "115425.6796875",
                        "WorstPrincipal-Minimum": "-115074.859375",
                        "XX-Maximum": "107958.6875",
                        "XX-Minimum": "-106925.3671875",
                        "XY-Maximum": "0.0",
                        "XY-Minimum": "0.0",
                        "YY-Maximum": "0.0",
                        "YY-Minimum": "0.0",
                        "YZ-Maximum": "0.0",
                        "YZ-Minimum": "0.0",
                        "ZX-Maximum": "26847.421875",
                        "ZX-Minimum": "-4996.708984375",
                        "ZZ-Maximum": "27080.06640625",
                        "ZZ-Minimum": "-26629.619140625"
                    },
                    "StressElementNodal_TOPEDGE_id_num_5--2Dmodel_sim2_CQUAD8_ElSize_1mm": {
                        "hasUnit": "milli-newton/mm^2",
                        "Determinant-Maximum": "0.0",
                        "Determinant-Minimum": "0.0",
                        "MaximumPrincipal-Maximum": "5850.52099609375",
                        "MaximumPrincipal-Minimum": "-2.1827872842550278e-11",
                        "MaximumShear-Maximum": "57537.4296875",
                        "MaximumShear-Minimum": "833.3782348632812",
                        "Mean-Maximum": "1238.54638671875",
                        "Mean-Minimum": "-44518.328125",
                        "MiddlePrincipal-Maximum": "1666.7928466796875",
                        "MiddlePrincipal-Minimum": "-18480.125",
                        "MinimumPrincipal-Maximum": "4.547473508864641e-13",
                        "MinimumPrincipal-Minimum": "-115074.859375",
                        "Octahedral-Maximum": "50458.21484375",
                        "Octahedral-Minimum": "680.4607543945312",
                        "VonMises-Maximum": "107038.0390625",
                        "VonMises-Minimum": "1443.4752197265625",
                        "WorstPrincipal-Maximum": "2048.859375",
                        "WorstPrincipal-Minimum": "-115074.859375",
                        "XX-Maximum": "2048.859375",
                        "XX-Minimum": "-106925.3671875",
                        "XY-Maximum": "0.0",
                        "XY-Minimum": "0.0",
                        "YY-Maximum": "0.0",
                        "YY-Minimum": "0.0",
                        "YZ-Maximum": "0.0",
                        "YZ-Minimum": "0.0",
                        "ZX-Maximum": "26847.421875",
                        "ZX-Minimum": "-522.295654296875",
                        "ZZ-Maximum": "5846.7373046875",
                        "ZZ-Minimum": "-26629.619140625"
                    }
                },
                "StressElemental": {
                    "StressElemental_Model_id_num_4--2Dmodel_sim2_CQUAD8_ElSize_1mm": {
                        "hasUnit": "milli-newton/mm^2",
                        "Determinant-Maximum": "0.0",
                        "Determinant-Minimum": "0.0",
                        "MaximumPrincipal-Maximum": "76298.40625",
                        "MaximumPrincipal-Minimum": "-1.0059011401608586e-09",
                        "MaximumShear-Maximum": "38149.203125",
                        "MaximumShear-Minimum": "833.5980224609375",
                        "Mean-Maximum": "28046.7421875",
                        "Mean-Minimum": "-26780.462890625",
                        "MiddlePrincipal-Maximum": "10068.599609375",
                        "MiddlePrincipal-Minimum": "-8567.322265625",
                        "MinimumPrincipal-Maximum": "2.1207231839071028e-05",
                        "MinimumPrincipal-Minimum": "-73956.828125",
                        "Octahedral-Maximum": "34268.9453125",
                        "Octahedral-Minimum": "680.69482421875",
                        "VonMises-Maximum": "72695.4140625",
                        "VonMises-Minimum": "1443.9718017578125",
                        "WorstPrincipal-Maximum": "76298.40625",
                        "WorstPrincipal-Minimum": "-73956.828125",
                        "XX-Maximum": "74214.25",
                        "XX-Minimum": "-71635.46875",
                        "XY-Maximum": "0.0",
                        "XY-Minimum": "0.0",
                        "YY-Maximum": "0.0",
                        "YY-Minimum": "0.0",
                        "YZ-Maximum": "0.0",
                        "YZ-Minimum": "0.0",
                        "ZX-Maximum": "12831.966796875",
                        "ZX-Minimum": "-10.618847846984863",
                        "ZZ-Maximum": "12960.44140625",
                        "ZZ-Minimum": "-11877.3271484375"
                    }
                }
            },
            "GenericParameters": {
                "MaxTemperature": ""
            }
        },
        "Plots": {
            "ContourPlots": {
                "ContactPressureContour": "",
                "ContactStatusContour": "",
                "PressureContour": "",
                "TotalPressureContour": "",
                "VelocityContour": ""
            },
            "DisplacementPlot": "",
            "XYPlots": {
                "MassAveragedTotalPressurePlot": "",
                "WallYPlus": ""
            },
            "StressPlot": {
                "PrincipalStressPlot": "",
                "VonMisesStressPlot": ""
            },
            "StrainPlot": ""
        }
    },
    "MeshElements": {
        "AxiSymmetricElement": "",
        "HexElement": "",
        "PrismLayer": "",
        "QuadElement": {
            "CQUAD8--2Dmodel_fem2_CQUAD8_ElSize_1mm": {}
        },
        "ShellElement": "",
        "TetrahedralElement": ""
    },
    "GeometricFeature": {
        "Body": "",
        "Curve": "",
        "Edge": {
            "LOADINGEDGE--2DMODEL": {},
            "TOPEDGE--2DMODEL": {}
        },
        "Face": "",
        "Line": {
            "Line4--2DMODEL": {}
        },
        "Point": ""
    },
    "Documentation": {
        "ConfluencePage": {
            "ConfluencePage_id_num_5--2Dmodel_sim2_CQUAD8_ElSize_1mm": {
                "WebSite": ""
            }
        },
        "PPT": {
            "PPT_id_num_5--2Dmodel_sim2_CQUAD8_ElSize_1mm": {
                "LocalStorage": [
                    "LocalStorage_id_num_6--2Dmodel_sim2_CQUAD8_ElSize_1mm"
                ]
            }
        }
    },
    "MeshVolume": {
        "2d_mesh(1)--2Dmodel_fem2_CQUAD8_ElSize_1mm": {
            "Mesh_Collector": "ThinShell(1)",
            "Mesh_name": "2d_mesh(1)",
            "Surface Curvature Based Size Variation": "50",
            "Surface Curvature Threshold": "0.505 mm",
            "SolidMaterial": [
                "AISI_Steel_4340"
            ],
            "MeshElements": [
                "CQUAD8--2Dmodel_fem2_CQUAD8_ElSize_1mm"
            ],
            "is2D": true,
            "is3D": false,
            "MinElementLength": "0.1",
            "NumElements": "30000",
            "NumNodes": "90801",
            "Length": [
                "ElementSize_1mm--2Dmodel_fem2_CQUAD8_ElSize_1mm"
            ]
        }
    },
    "Project": {
        "2d_cantilever_analysis": {
            "People": [
                "Shyam",
                "Chethan"
            ],
            "Mechanical": [
                "2Dmodel_sim2_CQUAD8_ElSize_1mm"
            ],
            "UpdateEvent": [
                "UpdateEvent_id_num_5--2Dmodel_sim2_CQUAD8_ElSize_1mm"
            ],
            "ProjectStartDate": 1608505200.0,
            "ProjectEndDate": 1634680800.0
        }
    },
    "UpdateEvent": {
        "UpdateEvent_id_num_5": {
            "Comment": "changed mesh parameters to CQUAD8_ElSize_1mm",
            "hasPredecessor": "2Dmodel_sim2",
            "hasSuccessor": ""
        }
    }
}